app/__init__.py
app/config.py
app/cli/__init__.py
app/cli/main.py
app/core/__init__.py
app/core/logger.py
app/core/runner.py
app/core/tasks.py
app/tasks/__init__.py
app/tasks/video_processing.py
app/utils/__init__.py
app/utils/helpers.py
octopus_queue-0.1.5.dist-info/METADATA
octopus_queue-0.1.5.dist-info/WHEEL
octopus_queue-0.1.5.dist-info/entry_points.txt
octopus_queue-0.1.5.dist-info/RECORD
